memo/__init__.py
memo/codegen.py
memo/comic.py
memo/core.py
memo/lib.py
memo/parse.py
memo/utils.py
memo/version.py
memo_lang-1.2.9.dist-info/licenses/LICENSE
memo_lang-1.2.9.dist-info/METADATA
memo_lang-1.2.9.dist-info/WHEEL
memo_lang-1.2.9.dist-info/top_level.txt
memo_lang-1.2.9.dist-info/RECORD
