Metadata-Version: 2.4
Name: memo-lang
Version: 1.2.9
Summary: A probabilistic programming language for reasoning about reasoning
Author: Kartik Chandra, Tony Chen
License: MIT License
Project-URL: Homepage, http://github.com/kach/memo
Project-URL: Repository, http://github.com/kach/memo.git
Project-URL: Issues, http://github.com/kach/memo/issues
Classifier: Topic :: Scientific/Engineering :: Artificial Intelligence
Classifier: Topic :: Software Development :: Compilers
Classifier: Topic :: Software Development :: Libraries :: Python Modules
Classifier: License :: OSI Approved :: MIT License
Requires-Python: >=3.12
License-File: LICENSE
Requires-Dist: jax
Dynamic: license-file
